{"commandline":"ffuf -u https://otub815.518but.com/FUZZ -H X-Forwarded-For: 127.0.0.1 -w api_wordlist.txt -mc 200,401,403,405 -o api_scan_results.json","time":"2026-01-03T15:04:58-05:00","results":[{"input":{"FUZZ":"login"},"position":10,"status":403,"length":263,"words":4,"lines":2,"redirectlocation":"","resultfile":"","url":"https://otub815.518but.com/login","host":"otub815.518but.com"},{"input":{"FUZZ":"v2/login"},"position":5,"status":403,"length":263,"words":4,"lines":2,"redirectlocation":"","resultfile":"","url":"https://otub815.518but.com/v2/login","host":"otub815.518but.com"},{"input":{"FUZZ":"v1/login"},"position":1,"status":403,"length":243,"words":4,"lines":2,"redirectlocation":"","resultfile":"","url":"https://otub815.518but.com/v1/login","host":"otub815.518but.com"},{"input":{"FUZZ":"v1/auth"},"position":2,"status":403,"length":263,"words":4,"lines":2,"redirectlocation":"","resultfile":"","url":"https://otub815.518but.com/v1/auth","host":"otub815.518but.com"},{"input":{"FUZZ":"signin"},"position":9,"status":403,"length":243,"words":4,"lines":2,"redirectlocation":"","resultfile":"","url":"https://otub815.518but.com/signin","host":"otub815.518but.com"},{"input":{"FUZZ":"auth/login"},"position":8,"status":403,"length":263,"words":4,"lines":2,"redirectlocation":"","resultfile":"","url":"https://otub815.518but.com/auth/login","host":"otub815.518but.com"},{"input":{"FUZZ":"v1/user"},"position":3,"status":403,"length":263,"words":4,"lines":2,"redirectlocation":"","resultfile":"","url":"https://otub815.518but.com/v1/user","host":"otub815.518but.com"},{"input":{"FUZZ":"api/login"},"position":6,"status":403,"length":263,"words":4,"lines":2,"redirectlocation":"","resultfile":"","url":"https://otub815.518but.com/api/login","host":"otub815.518but.com"},{"input":{"FUZZ":"v1/admin"},"position":4,"status":403,"length":263,"words":4,"lines":2,"redirectlocation":"","resultfile":"","url":"https://otub815.518but.com/v1/admin","host":"otub815.518but.com"},{"input":{"FUZZ":"api/auth"},"position":7,"status":403,"length":263,"words":4,"lines":2,"redirectlocation":"","resultfile":"","url":"https://otub815.518but.com/api/auth","host":"otub815.518but.com"}],"config":{"headers":{"X-Forwarded-For":"127.0.0.1"},"extensions":[],"dirsearch_compatibility":false,"method":"GET","url":"https://otub815.518but.com/FUZZ","postdata":"","quiet":false,"colors":false,"inputproviders":[{"name":"wordlist","keyword":"FUZZ","value":"api_wordlist.txt"}],"cmd_inputnum":100,"inputmode":"clusterbomb","outputdirectory":"","outputfile":"api_scan_results.json","outputformat":"json","ignorebody":false,"ignore_wordlist_comments":false,"stop_403":false,"stop_errors":false,"stop_all":false,"follow_redirects":false,"autocalibration":false,"autocalibration_strings":[],"timeout":10,"delay":{"value":"0.00"},"filters":{},"matchers":{"status":{"value":"200,401,403,405"}},"threads":40,"proxyurl":"","replayproxyurl":"","cmdline":"ffuf -u https://otub815.518but.com/FUZZ -H X-Forwarded-For: 127.0.0.1 -w api_wordlist.txt -mc 200,401,403,405 -o api_scan_results.json","verbose":false,"maxtime":0,"maxtime_job":0,"recursion":false,"recursion_depth":0}}